pycalib/__init__.py
pycalib/ba.py
pycalib/bal.py
pycalib/calib.py
pycalib/circle.py
pycalib/diamond.py
pycalib/mirror.py
pycalib/plot.py
pycalib/robust.py
pycalib/rotation.py
pycalib/sphere.py
pycalib/stereo.py
pycalib/timestamp.py
pycalib/util.py
pycalib_simple-2025.12.5.1.dist-info/LICENSE
pycalib_simple-2025.12.5.1.dist-info/METADATA
pycalib_simple-2025.12.5.1.dist-info/WHEEL
pycalib_simple-2025.12.5.1.dist-info/top_level.txt
pycalib_simple-2025.12.5.1.dist-info/RECORD
