Metadata-Version: 2.1
Name: pycalib-simple
Version: 2025.12.5.1
Summary: PyCalib: Simple Camera Calibration in Python for Beginners
Home-page: https://github.com/nbhr/pycalib
Download-URL: https://github.com/nbhr/pycalib
Author: Shohei Nobuhara
Author-email: nob@ieee.org
Maintainer: Shohei Nobuhara
Maintainer-email: nob@ieee.org
License: Apache Software License
Classifier: Intended Audience :: Science/Research
Classifier: License :: OSI Approved :: Apache Software License
Classifier: Programming Language :: Python :: 3
Classifier: Programming Language :: Python :: 3.6
Classifier: Programming Language :: Python :: 3.7
Classifier: Programming Language :: Python :: 3.8
Classifier: Programming Language :: Python :: 3.9
Classifier: Programming Language :: Python :: 3.10
Classifier: Programming Language :: Python :: 3.11
Classifier: Programming Language :: Python :: 3 :: Only
Classifier: Topic :: Scientific/Engineering
Classifier: Topic :: Scientific/Engineering :: Image Processing
Classifier: Topic :: Scientific/Engineering :: Image Recognition
Classifier: Framework :: Matplotlib
Classifier: Framework :: Jupyter
Requires-Python: >=3.6
License-File: LICENSE
Requires-Dist: matplotlib (>=3.5.1)
Requires-Dist: numpy (>=1.22.0)
Requires-Dist: opencv-contrib-python (>=4.5.5.62)
Requires-Dist: scikit-image (>=0.19.1)
Requires-Dist: scipy (>=1.7.3)
